aioWiserHeatAPI/__init__.py
aioWiserHeatAPI/automation.py
aioWiserHeatAPI/binary_sensor.py
aioWiserHeatAPI/boiler_interface.py
aioWiserHeatAPI/button_panel.py
aioWiserHeatAPI/cli.py
aioWiserHeatAPI/const.py
aioWiserHeatAPI/devices.py
aioWiserHeatAPI/discovery.py
aioWiserHeatAPI/exceptions.py
aioWiserHeatAPI/heating.py
aioWiserHeatAPI/heating_actuator.py
aioWiserHeatAPI/hot_water.py
aioWiserHeatAPI/light.py
aioWiserHeatAPI/moments.py
aioWiserHeatAPI/ptc.py
aioWiserHeatAPI/pte.py
aioWiserHeatAPI/refactor.py
aioWiserHeatAPI/rest_controller.py
aioWiserHeatAPI/room.py
aioWiserHeatAPI/roomstat.py
aioWiserHeatAPI/schedule.py
aioWiserHeatAPI/shutter.py
aioWiserHeatAPI/smartplug.py
aioWiserHeatAPI/smartvalve.py
aioWiserHeatAPI/smokealarm.py
aioWiserHeatAPI/system.py
aioWiserHeatAPI/temp_humidity.py
aioWiserHeatAPI/ufh.py
aioWiserHeatAPI/wiserhub.py
aioWiserHeatAPI/helpers/__init__.py
aioWiserHeatAPI/helpers/automations.py
aioWiserHeatAPI/helpers/battery.py
aioWiserHeatAPI/helpers/capabilities.py
aioWiserHeatAPI/helpers/cloud.py
aioWiserHeatAPI/helpers/device.py
aioWiserHeatAPI/helpers/equipment.py
aioWiserHeatAPI/helpers/extra_config.py
aioWiserHeatAPI/helpers/firmware.py
aioWiserHeatAPI/helpers/gps.py
aioWiserHeatAPI/helpers/misc.py
aioWiserHeatAPI/helpers/network.py
aioWiserHeatAPI/helpers/opentherm.py
aioWiserHeatAPI/helpers/signal.py
aioWiserHeatAPI/helpers/special_times.py
aioWiserHeatAPI/helpers/status.py
aioWiserHeatAPI/helpers/temp.py
aioWiserHeatAPI/helpers/threshold.py
aioWiserHeatAPI/helpers/uiconfiguration.py
aioWiserHeatAPI/helpers/version.py
aioWiserHeatAPI/helpers/zigbee.py
aiowiserheatapi-1.7.0.dist-info/licenses/LICENSE
aiowiserheatapi-1.7.0.dist-info/METADATA
aiowiserheatapi-1.7.0.dist-info/WHEEL
aiowiserheatapi-1.7.0.dist-info/entry_points.txt
aiowiserheatapi-1.7.0.dist-info/top_level.txt
aiowiserheatapi-1.7.0.dist-info/RECORD
