Metadata-Version: 2.4
Name: aioWiserHeatAPI
Version: 1.7.0
Summary: An AsyncIO API for controlling the Drayton Wiser Heating system
Home-page: https://github.com/msp1974/aioWiserHeatAPI
Author: Mark Parker
Author-email: msparker@sky.com
Classifier: Development Status :: 5 - Production/Stable
Classifier: Intended Audience :: Developers
Classifier: Programming Language :: Python :: 3.11
Classifier: License :: OSI Approved :: MIT License
Classifier: Operating System :: OS Independent
Requires-Python: >=3.12
License-File: LICENSE
Requires-Dist: zeroconf>=0.131.0
Requires-Dist: aiohttp>=3.9.3
Requires-Dist: aiofiles>=23.2.1
Requires-Dist: pyyaml>=6.0.1
Dynamic: author
Dynamic: author-email
Dynamic: classifier
Dynamic: description
Dynamic: description-content-type
Dynamic: home-page
Dynamic: license-file
Dynamic: requires-dist
Dynamic: requires-python
Dynamic: summary
